{
  "date": "2026-03-15",
  "date_label": "March 15, 2026",
  "yesterday_label": "March 14",
  "n_games": 6,
  "n_sig1": 0,
  "n_partial": 0,
  "games_tonight": [
    {
      "away": "SJS",
      "home": "OTT",
      "away_city": "San Jose",
      "away_name": "Sharks",
      "home_city": "Ottawa",
      "home_name": "Senators",
      "time_et": "5:00 PM ET",
      "time_mt": "3:00 PM MT",
      "signal": "cancel",
      "away_b2b": true,
      "home_b2b": true,
      "home_rest": 1,
      "away_ml": "+170",
      "home_ml": "-205"
    },
    {
      "away": "ANA",
      "home": "MTL",
      "away_city": "Anaheim",
      "away_name": "Ducks",
      "home_city": "Montr\u00e9al",
      "home_name": "Canadiens",
      "time_et": "7:00 PM ET",
      "time_mt": "5:00 PM MT",
      "signal": "cancel",
      "away_b2b": true,
      "home_b2b": true,
      "home_rest": 1,
      "away_ml": null,
      "home_ml": null
    },
    {
      "away": "TOR",
      "home": "MIN",
      "away_city": "Toronto",
      "away_name": "Maple Leafs",
      "home_city": "Minnesota",
      "home_name": "Wild",
      "time_et": "7:30 PM ET",
      "time_mt": "5:30 PM MT",
      "signal": "cancel",
      "away_b2b": true,
      "home_b2b": true,
      "home_rest": 1,
      "away_ml": "+205",
      "home_ml": "-250"
    },
    {
      "away": "STL",
      "home": "WPG",
      "away_city": "St. Louis",
      "away_name": "Blues",
      "home_city": "Winnipeg",
      "home_name": "Jets",
      "time_et": "3:00 PM ET",
      "time_mt": "1:00 PM MT",
      "signal": "none",
      "away_b2b": false,
      "home_b2b": true,
      "home_rest": 1,
      "away_ml": null,
      "home_ml": null
    },
    {
      "away": "NSH",
      "home": "EDM",
      "away_city": "Nashville",
      "away_name": "Predators",
      "home_city": "Edmonton",
      "home_name": "Oilers",
      "time_et": "8:00 PM ET",
      "time_mt": "6:00 PM MT",
      "signal": "none",
      "away_b2b": false,
      "home_b2b": false,
      "home_rest": 2,
      "away_ml": "+154",
      "home_ml": "-185"
    },
    {
      "away": "FLA",
      "home": "SEA",
      "away_city": "Florida",
      "away_name": "Panthers",
      "home_city": "Seattle",
      "home_name": "Kraken",
      "time_et": "8:00 PM ET",
      "time_mt": "6:00 PM MT",
      "signal": "none",
      "away_b2b": false,
      "home_b2b": true,
      "home_rest": 1,
      "away_ml": "-130",
      "home_ml": "+110"
    }
  ],
  "last_night": [
    {
      "away": "ANA",
      "home": "OTT",
      "away_score": 0,
      "home_score": 2,
      "signal": "none",
      "result": "none",
      "note": "No signal \u00b7 Neither team on B2B",
      "fade_won": true
    },
    {
      "away": "BOS",
      "home": "WSH",
      "away_score": 3,
      "home_score": 2,
      "signal": "none",
      "result": "none",
      "note": "No signal \u00b7 Neither team on B2B",
      "fade_won": false
    },
    {
      "away": "COL",
      "home": "WPG",
      "away_score": 1,
      "home_score": 3,
      "signal": "none",
      "result": "none",
      "note": "No signal \u00b7 Neither team on B2B",
      "fade_won": true
    },
    {
      "away": "NYR",
      "home": "MIN",
      "away_score": 4,
      "home_score": 2,
      "signal": "none",
      "result": "none",
      "note": "No signal \u00b7 Neither team on B2B",
      "fade_won": false
    },
    {
      "away": "TOR",
      "home": "BUF",
      "away_score": 2,
      "home_score": 3,
      "signal": "none",
      "result": "none",
      "note": "No signal \u00b7 Neither team on B2B",
      "fade_won": true
    },
    {
      "away": "SJS",
      "home": "MTL",
      "away_score": 4,
      "home_score": 2,
      "signal": "none",
      "result": "none",
      "note": "No signal \u00b7 Neither team on B2B",
      "fade_won": false
    },
    {
      "away": "CAR",
      "home": "TBL",
      "away_score": 4,
      "home_score": 2,
      "signal": "none",
      "result": "none",
      "note": "No signal \u00b7 Neither team on B2B",
      "fade_won": false
    },
    {
      "away": "LAK",
      "home": "NJD",
      "away_score": 4,
      "home_score": 6,
      "signal": "partial",
      "result": "hit",
      "note": "LAK on B2B away \u00b7 NJD rested 2 days \u2192 Signal 1 Partial",
      "fade_won": true
    },
    {
      "away": "CGY",
      "home": "NYI",
      "away_score": 2,
      "home_score": 3,
      "signal": "none",
      "result": "none",
      "note": "No signal \u00b7 Neither team on B2B",
      "fade_won": true
    },
    {
      "away": "CBJ",
      "home": "PHI",
      "away_score": 2,
      "home_score": 1,
      "signal": "none",
      "result": "none",
      "note": "No signal \u00b7 Neither team on B2B",
      "fade_won": false
    },
    {
      "away": "DET",
      "home": "DAL",
      "away_score": 2,
      "home_score": 3,
      "signal": "none",
      "result": "none",
      "note": "No signal \u00b7 Neither team on B2B",
      "fade_won": true
    },
    {
      "away": "PIT",
      "home": "UTA",
      "away_score": 4,
      "home_score": 3,
      "signal": "none",
      "result": "none",
      "note": "No signal \u00b7 Neither team on B2B",
      "fade_won": false
    },
    {
      "away": "SEA",
      "home": "VAN",
      "away_score": 5,
      "home_score": 2,
      "signal": "none",
      "result": "none",
      "note": "No signal \u00b7 Neither team on B2B",
      "fade_won": false
    },
    {
      "away": "CHI",
      "home": "VGK",
      "away_score": 0,
      "home_score": 4,
      "signal": "none",
      "result": "none",
      "note": "No signal \u00b7 Neither team on B2B",
      "fade_won": true
    }
  ],
  "lookahead": [
    {
      "date": "2026-03-17",
      "date_label": "Tuesday, March 17",
      "away": "BOS",
      "home": "MTL",
      "signal": "partial",
      "away_b2b": true,
      "home_b2b": false,
      "home_rest": 2,
      "time_et": "7:00 PM ET"
    }
  ]
}