{
  "date": "2026-03-30",
  "updated": "11:16 PM MT",
  "games": [
    {
      "away": "PIT",
      "home": "NYI",
      "away_city": "Pittsburgh",
      "home_city": "New York",
      "away_score": 8,
      "home_score": 3,
      "status": "final",
      "display": "Final",
      "period_label": "3rd"
    },
    {
      "away": "CGY",
      "home": "COL",
      "away_city": "Calgary",
      "home_city": "Colorado",
      "away_score": 2,
      "home_score": 9,
      "status": "final",
      "display": "Final",
      "period_label": "3rd"
    },
    {
      "away": "VAN",
      "home": "VGK",
      "away_city": "Vancouver",
      "home_city": "Vegas",
      "away_score": 2,
      "home_score": 4,
      "status": "final",
      "display": "Final",
      "period_label": "3rd"
    },
    {
      "away": "TOR",
      "home": "ANA",
      "away_city": "Toronto",
      "home_city": "Anaheim",
      "away_score": 5,
      "home_score": 4,
      "status": "final",
      "display": "Final/OT",
      "period_label": "OT"
    },
    {
      "away": "STL",
      "home": "SJS",
      "away_city": "St. Louis",
      "home_city": "San Jose",
      "away_score": 4,
      "home_score": 5,
      "status": "final",
      "display": "Final",
      "period_label": "3rd"
    }
  ]
}