{
  "date": "2026-04-23",
  "updated": "11:57 PM MT",
  "games": [
    {
      "away": "BUF",
      "home": "BOS",
      "away_city": "Buffalo",
      "home_city": "Boston",
      "away_score": 3,
      "home_score": 1,
      "status": "final",
      "display": "Final",
      "period_label": "3rd"
    },
    {
      "away": "CAR",
      "home": "OTT",
      "away_city": "Carolina",
      "home_city": "Ottawa",
      "away_score": 2,
      "home_score": 1,
      "status": "final",
      "display": "Final",
      "period_label": "3rd"
    },
    {
      "away": "COL",
      "home": "LAK",
      "away_city": "Colorado",
      "home_city": "Los Angeles",
      "away_score": 4,
      "home_score": 2,
      "status": "final",
      "display": "Final",
      "period_label": "3rd"
    }
  ]
}